AUTHORS
LICENSE
README.rst
setup.py
yandex_tracker_client/__init__.py
yandex_tracker_client/client.py
yandex_tracker_client/collections.py
yandex_tracker_client/connection.py
yandex_tracker_client/exceptions.py
yandex_tracker_client/objects.py
yandex_tracker_client/settings.py
yandex_tracker_client/uriutils.py
yandex_tracker_client.egg-info/PKG-INFO
yandex_tracker_client.egg-info/SOURCES.txt
yandex_tracker_client.egg-info/dependency_links.txt
yandex_tracker_client.egg-info/requires.txt
yandex_tracker_client.egg-info/top_level.txt