Metadata-Version: 2.1
Name: yandex-tracker-client
Version: 2.9
Summary: Client for Yandex.Tracker
Home-page: https://github.com/yandex/yandex_tracker_client
Author: Yandex Team
Author-email: smosker@yandex-team.ru
License: UNKNOWN
Keywords: python yandex.tracker api-client
Platform: UNKNOWN
Classifier: Development Status :: 5 - Production/Stable
Classifier: Intended Audience :: Developers
Classifier: License :: OSI Approved :: BSD License
Classifier: Operating System :: OS Independent
Classifier: Topic :: Software Development :: Libraries :: Python Modules
Classifier: Programming Language :: Python
Classifier: Programming Language :: Python :: 3
Classifier: Programming Language :: Python :: 2
Requires-Python: >=2.7
License-File: LICENSE
License-File: AUTHORS
